Workbook

Sheet Read Me
A1: AI-Native Product Prioritization Maturity Model
A2: Version 1.0 · Final draft · Three dimension-specific A–E maturity ladders
A3: Note on versioning: "Version 1.0" above is this workbook's own personal file-versioning, not a claim about the AI-Native Maturity Model family's formal governance-lock status (which uses the same v0.9/v1.0 language to mean something specific and separately decided). The two version counters are independent; this workbook reaching "1.0" does not mean the family has formally locked it.
A4: Purpose
A5: This model appraises an organization's product prioritization capability—not the elegance of a single scorecard or roadmap decision. Level A is the least mature state; Level E is the most mature. Each step describes a realistically adjacent operating state specific to the dimension.
A8: AI-native design rule
A9: AI use does not increase maturity by itself. It increases maturity only when it improves evidence quality, decision coherence, traceability, calibration, or adaptation without obscuring authority or converting inference into fact. The model therefore moves from incidental AI use, to governed participation, to independent challenge, and finally to closed-loop learning.
A14: The three dimensions
A15: ID | B15: Dimension | C15: Core question
A16: D1 | B16: Value Model Coherence | C16: Is product value explicit, multi-dimensional, defensible, and usable by governed human and AI participants?
A17: D2 | B17: Decision Governance & Portfolio Integration | C17: Do those value judgments govern real funding, capacity, sequencing, and trade-offs, with explicit human and AI authority?
A18: D3 | B18: Outcome Calibration & Adaptation | C18: Does realized evidence improve forecasts, the value model, portfolio decisions, and—when warranted—the originating intent?
A20: The governing loop
A21: The governing loop: enterprise intent → D1 value model → D2 portfolio decision → execution and outcomes → D3 calibration → portfolio/model correction → reconsideration of enterprise intent when the evidence indicates possible intent failure. D3-E is the capstone: it distinguishes execution failure, forecasting error, model error, and possible intent failure, then routes each to its proper authority.
A33: The 2015 Strategic Value Matrix -- authored by David, predating this model by over a decade -- is the reference pattern for Level E Value Model Coherence: explicit multi-factor value logic, visible weights, and explainable trade-offs. Overall Level E still requires comparable maturity in decision governance and closed-loop intent calibration.
A37: How to use this workbook
A38: 1 | B38: Read each dimension's full A–E ladder on the Maturity Matrix sheet.
A39: 2 | B39: Score the normal operating capability—not the best team, workshop, artifact, or AI demonstration.
A40: 3 | B40: Record evidence for the current grade on the Assessment sheet.
A41: 4 | B41: Treat the three-grade profile as authoritative; the overall grade is only a directional summary.
A42: 5 | B42: Prefer proximate improvement: use the current level's transition statement as the next design target.

Sheet Maturity Matrix
A1: AI-Native Product Prioritization Maturity Model
A2: Dimension-specific A–E ladders · A is lowest maturity; E is highest maturity
A4: D1. Value Model Coherence
A5: The capability to define and maintain an explicit model of product value that makes unlike drivers comparable without collapsing them—including strategic, customer, market, economic, architectural, delivery, risk, and debt considerations. AI becomes relevant only when it can use, challenge, or help improve that governed model.
A6: Level | B6: Dimension-specific state | C6: Maturity definition | D6: Indicative evidence | E6: Transition to next level
A7: A | B7: Nascent | C7: Priority is determined mainly by advocacy, urgency, executive request, anecdote, or estimated effort. Individuals may use AI privately to draft business cases or make a preferred item sound more compelling, but there is no stable value model against which the output can be tested. | D7: Roadmaps built from requests; inconsistent rationale; private AI-generated business cases; value and effort discussed as one undifferentiated judgment. | E7: Name a small common set of criteria, separate value from implementation difficulty, and require the same logic for every candidate.
A8: B | B8: Modeled | C8: A common prioritization method is used—such as value-versus-effort, RICE, MoSCoW, or a simple weighted score. AI may summarize proposals, normalize submissions, or collect preliminary evidence, but criteria remain generic, scoring anchors are weak, and humans manually translate AI output into the model. | D8: Reusable scorecard; simple ranking; AI-assisted proposal summaries; shared criteria with limited definitions; workshop-dependent interpretation. | E8: Define dimension-specific criteria and scoring anchors, state the evidence expected for material scores, and preserve source provenance.
A9: C | B9: Continuous | C9: The organization uses a shared product-value model with distinct scoring dimensions, defined scales, and explicit separation of business value from implementation difficulty. The model is structured enough that AI can map proposals to criteria, assemble cited evidence, identify missing inputs, and flag inconsistent scoring. Humans retain responsibility for weights and final value judgment. | D9: Defined scales and weights; separate business-value and implementation factors; machine-readable scoring structure; cited evidence; AI-flagged gaps or inconsistencies. | E9: Assign formal ownership, version the model, test criteria for overlap or double-counting, and make assumptions, confidence, and exceptions visible.
A10: D | B10: Integral | C10: The value model is formally owned, versioned, and tied to current strategy and portfolio context. AI performs scenario and sensitivity analysis, challenges unsupported assumptions, detects likely double-counting or scoring drift, and explains why rankings change. The model, weights, evidence standards, and decision authority remain human-governed. | D10: Model owner; version history; criterion provenance; AI-supported sensitivity analysis; confidence notes; scoring-drift review; documented exceptions. | E10: Connect the value model to realized outcomes so evidence can recalibrate scoring anchors, weights, and strategic assumptions.
A11: E | B11: Telemetric | C11: A multi-factor strategic value system—of the kind represented by the Strategic Value Matrix—balances revenue magnitude and velocity, strategic alignment, market and customer fit, architecture, implementation size, technical-debt reduction, and delivery risk through explicit scales and weights. AI continuously refreshes relevant evidence, detects model or strategy drift, and proposes changes to criteria, anchors, or weights. Every change remains explainable, versioned, and human-authorized, and the organization can reconstruct why one item outranked another at any point in time. | D11: Governed strategic value matrix; transparent positive and negative drivers; continuously refreshed evidence; explainable scenarios; model-drift detection; preserved decision history. | E11: Sustain empirical and strategic integrity: verify that evidence refresh improves the model without allowing automation, recency, or persuasive inference to redefine value silently.
A13: D2. Decision Governance & Portfolio Integration
A14: The capability to turn value judgments into transparent, authoritative portfolio choices that account for funding, capacity, dependencies, sequencing, exceptions, and displacement of other work. AI becomes relevant only when its role, evidence obligations, and authority limits are explicit.
A15: Level | B15: Dimension-specific state | C15: Maturity definition | D15: Indicative evidence | E15: Transition to next level
A16: A | B16: Nascent | C16: Prioritization is a series of local decisions made by the loudest stakeholder, highest-ranking executive, or most urgent customer request. AI may be used privately to strengthen advocacy, but its evidence, reasoning, and influence are invisible. There is no stable decision forum, no visible displacement of other work, and little distinction between recommending, approving, and committing. | D16: Unrecorded overrides; backlog churn; private AI-generated narratives; urgent work inserted without explicit trade-off; no portfolio-level decision record. | E16: Create a recurring decision forum and name who proposes, challenges, decides, records, and commits the outcome.
A17: B | B17: Modeled | C17: A scorecard or ranking is used in recurring prioritization meetings, and decisions are documented. AI may prepare summaries, compare proposals, expose obvious conflicts, or record rationale, but it has no governed role and lacks complete access to capacity, funding, dependencies, sequencing, and portfolio context. Executives may still override the result without a standard exception path. | D17: Recurring workshop; ranked list; AI-generated meeting preparation; documented decisions; limited constraint analysis; informal overrides. | E17: Define decision rights, an exception path, the portfolio constraints that must be applied, and the specific AI role in evidence assembly and analysis.
A18: C | B18: Continuous | C18: Scoring, challenge, approval, exception, and commitment are distinct and traceable. AI roles and limits are explicit: AI assembles evidence, checks candidate completeness, verifies dependencies and capacity constraints, and records provenance; named humans make consequential decisions. Funding, sequencing, risk, and portfolio balance constrain the ranked list, and the result directly governs committed work within a portfolio. | D18: Decision log; named authorities; governed AI role; evidence provenance; capacity plan; dependency view; exception record; roadmap traceability. | E18: Extend the same decision system across Product, Engineering, Architecture, Finance, and go-to-market portfolios, with common scenario semantics.
A19: D | B19: Integral | C19: A shared prioritization system operates across functions and product areas. AI traverses product, engineering, architecture, finance, customer, and go-to-market evidence to model displacement and second-order effects. Independent analysis can challenge the originating proposal and show what is delayed, unfunded, or made riskier when one investment advances. Humans govern the scenarios, thresholds, and final commitments. | D19: Cross-portfolio scenarios; integrated funding and capacity views; AI-supported displacement analysis; independent challenge; architecture and dependency impacts. | E19: Reduce the latency between material evidence changes and governed reconsideration while preserving authority, evidence, and exception discipline.
A20: E | B20: Telemetric | C20: Prioritization operates as a standing management system rather than an episodic workshop. New demand enters through a known path; comparable evidence is assembled; alternatives are challenged; and capacity, funding, dependencies, sequencing, and portfolio balance are resolved continuously. AI monitors material changes, maintains decision-ready scenarios, and initiates governed reconsideration. Routine low-consequence actions may be delegated within explicit authority, while consequential portfolio choices remain visibly human-owned. | D20: Governed intake-to-commit flow; live portfolio scenarios; event-driven reconsideration; bounded AI authority; rapid but traceable continue, pause, stop, accelerate, and reallocate decisions. | E20: Continuously test whether adaptive speed is preserving strategic coherence and constitutional authority rather than amplifying short-term noise.
A22: D3. Outcome Calibration & Adaptation
A23: The capability to compare predicted value, effort, timing, and risk with realized outcomes; distinguish execution, forecast, model, and intent failure; and return the findings to the portfolio, value model, and—when warranted—the originating enterprise intent.
A24: Level | B24: Dimension-specific state | C24: Maturity definition | D24: Indicative evidence | E24: Transition to next level
A25: A | B25: Nascent | C25: Once work is approved, the prioritization decision is rarely revisited. Delivery may be tracked, and AI may summarize results after the fact, but the original value hypothesis, evidence, assumptions, and intended outcome are not preserved well enough to determine whether the decision was right. | D25: Shipped equals successful; no benefits review; no record of original assumptions; post-hoc AI summaries without a comparison baseline. | E25: For every material decision, preserve the expected outcome, measure, owner, review date, underlying value hypothesis, and originating intent.
A26: B | B26: Modeled | C26: Major initiatives receive occasional after-action review. AI helps synthesize retrospectives and compare planned versus actual effort, timing, or selected business outcomes, but the analysis is episodic and selective. Lessons usually affect the next project informally rather than changing the prioritization model or portfolio. | D26: Project retrospectives; AI-assisted synthesis; planned-versus-actual delivery review; informal benefits discussion; isolated lessons. | E26: Require consistent outcome hypotheses and scheduled reviews, and link realized evidence back to the original decision rather than only to delivery performance.
A27: C | B27: Continuous | C27: Material prioritization decisions carry explicit expected outcomes, measures, timing, ownership, value hypotheses, and originating intent. AI connects the original decision to subsequent customer, market, financial, delivery, architectural, debt, and risk evidence, flags material variance, and keeps verified evidence, reported information, assumptions, and inference visibly distinct. | D27: Benefits register; decision-to-outcome traceability; named outcome owner; AI-assembled evidence package; forecast-versus-actual review; model-change log. | E27: Measure forecast accuracy and recurring bias by criterion, investment type, product area, and decision team, using independent analysis where practical.
A28: D | B28: Integral | C28: AI identifies where the organization systematically overstates value, understates effort, misses timing, discounts risk, or misreads evidence. Forecast accuracy and bias are measured by criterion, team, product area, and investment type. Scoring anchors, confidence ranges, weights, and governance practices are adjusted empirically, and continue, expand, pause, or stop decisions occur before all planned investment is consumed. | D28: Bias analysis; criterion calibration; confidence ranges; independent AI review; stage decisions; evidence-based model revisions; preserved decision lineage. | E28: Close the loop to enterprise intent: distinguish execution failure, forecast error, model error, and possible intent failure, then route each to its proper authority.
A29: E | B29: Telemetric | C29: Product prioritization operates as a continuous learning loop. Customer, market, financial, delivery, architectural, debt, and risk evidence is traced back to the original value hypothesis and the intent it served. AI assistance detects variance, systematic bias, model drift, and emerging opportunity while work is still underway, distinguishing execution failure from forecasting error, model error, and possible intent failure. The portfolio, prioritization model, and—when warranted—the originating intent can each be reconsidered through their proper authority, without losing decision lineage or converting inference into fact. | D29: Continuous outcome signals; intent-to-decision-to-outcome traceability; failure-class diagnosis; model-drift checks; early continue, pause, stop, or redirect decisions; preserved evidence and authority lineage. | E29: Sustain epistemic and constitutional discipline: ensure the loop can challenge intent without allowing AI inference to silently become enterprise intent.

Sheet Assessment
A1: AI-Native Product Prioritization Maturity Assessment
A2: Select current and target grades. Record evidence of normal operating behavior—not tool adoption alone.
A4: Summary | B4: Value | D4: Metric | E4: Value
A5: Overall Grade | B5: =IF(E5="","",CHOOSE(ROUND(E5,0),"A","B","C","D","E")) | D5: Average Score | E5: =IF(COUNT(C11:C13)=0,"",AVERAGE(C11:C13))
A6: Lowest Dimension | B6: =IF(COUNT(C11:C13)<3,"",INDEX(A11:A13,MATCH(MIN(C11:C13),C11:C13,0))) | D6: Completed Dimensions | E6: =COUNT(C11:C13)
A7: Grade Spread | B7: =IF(COUNT(C11:C13)<3,"",MAX(C11:C13)-MIN(C11:C13)) | D7: Interpretation | E7: =IF(E6=0,"Not started",IF(E6<3,"Partial profile",IF(B7>1,"Material maturity gap—improve the constrained dimension first","Balanced profile")))
A10: Dimension | B10: Current Grade | C10: Current Score | D10: Current Level | E10: Target Grade | F10: Target Score | G10: Gap | H10: Evidence / Notes | I10: Typical Next Step
A11: Value Model Coherence | C11: =IF(B11="","",IF(B11="A",1,IF(B11="B",2,IF(B11="C",3,IF(B11="D",4,5))))) | D11: =IF(B11="","",VLOOKUP("D1|"&B11,Reference!$F$2:$M$16,5,FALSE)) | F11: =IF(E11="","",IF(E11="A",1,IF(E11="B",2,IF(E11="C",3,IF(E11="D",4,5))))) | G11: =IF(OR(C11="",F11=""),"",F11-C11) | I11: =IF(B11="","",VLOOKUP("D1|"&B11,Reference!$F$2:$M$16,8,FALSE))
A12: Decision Governance & Portfolio Integration | C12: =IF(B12="","",IF(B12="A",1,IF(B12="B",2,IF(B12="C",3,IF(B12="D",4,5))))) | D12: =IF(B12="","",VLOOKUP("D2|"&B12,Reference!$F$2:$M$16,5,FALSE)) | F12: =IF(E12="","",IF(E12="A",1,IF(E12="B",2,IF(E12="C",3,IF(E12="D",4,5))))) | G12: =IF(OR(C12="",F12=""),"",F12-C12) | I12: =IF(B12="","",VLOOKUP("D2|"&B12,Reference!$F$2:$M$16,8,FALSE))
A13: Outcome Calibration & Adaptation | C13: =IF(B13="","",IF(B13="A",1,IF(B13="B",2,IF(B13="C",3,IF(B13="D",4,5))))) | D13: =IF(B13="","",VLOOKUP("D3|"&B13,Reference!$F$2:$M$16,5,FALSE)) | F13: =IF(E13="","",IF(E13="A",1,IF(E13="B",2,IF(E13="C",3,IF(E13="D",4,5))))) | G13: =IF(OR(C13="",F13=""),"",F13-C13) | I13: =IF(B13="","",VLOOKUP("D3|"&B13,Reference!$F$2:$M$16,8,FALSE))

Sheet Evidence Guide
A1: Assessment Evidence & Interview Guide
A2: A sophisticated artifact or widespread AI use does not, by itself, prove mature prioritization. Appraise the operating capability and its evidence.
A4: Dimension | B4: Diagnostic Question | C4: Evidence to Request | D4: Lower-Maturity Signal | E4: Higher-Maturity Signal | F4: Assessment Note
A5: Value Model Coherence | B5: What distinct factors make one product investment more valuable than another? | C5: Criteria, definitions, scoring anchors, weights | D5: Priority reduces to urgency, executive preference, or persuasive narrative | E5: Distinct value and feasibility dimensions with defined scales and visible weights
A6: Value Model Coherence | B6: Can AI use the model directly without a human rewriting every proposal into a fresh prompt? | C6: Structured scorecard, canonical candidate fields, criterion definitions | D6: AI use is private and prompt-dependent | E6: The governed model is machine-readable and reusable across candidates
A7: Value Model Coherence | B7: Does AI assemble evidence or merely manufacture justification? | C7: Source references, provenance, assumptions, confidence notes | D7: AI-generated scores or claims appear without sources | E7: Evidence, uncertainty, and inference remain visible and separable
A8: Value Model Coherence | B8: Can the organization explain why the ranking changes? | C8: Sensitivity analysis, alternate weighting scenarios, version history | D8: Weights change informally or to produce a preferred answer | E8: AI-supported scenarios remain explainable, governed, and historically reconstructable
A9: Value Model Coherence | B9: Does the model learn without silently redefining value? | C9: Outcome calibration, model-change proposals, approval record | D9: Automation or recency alters criteria implicitly | E9: AI proposes model changes; humans authorize them through visible governance
A10: Decision Governance & Portfolio Integration | B10: Who proposes, challenges, decides, commits, and records? | C10: Decision rights, forum charter, exception path | D10: Authority changes by personality or meeting attendance | E10: Distinct human and AI roles with explicit limits and escalation
A11: Decision Governance & Portfolio Integration | B11: What constrains a ranked list before it becomes a roadmap? | C11: Capacity plan, funding view, dependency map, sequencing constraints | D11: Ranking ignores constraints until delivery starts | E11: Funding, capacity, dependency, and sequencing shape the decision before commitment
A12: Decision Governance & Portfolio Integration | B12: Can AI see cross-functional displacement and second-order effects? | C12: Integrated portfolio scenarios, architecture and financial relationships | D12: AI summarizes proposals in isolation | E12: AI traverses governed portfolio context and exposes what is displaced or made riskier
A13: Decision Governance & Portfolio Integration | B13: Are overrides and delegated actions visible? | C13: Exception log, bounded-authority rules, decision records | D13: Executives or agents act outside the model without traceability | E13: Every exception or delegated action names authority, rationale, scope, and consequence
A14: Decision Governance & Portfolio Integration | B14: Can material evidence trigger reconsideration without a political reset? | C14: Event-driven reviews, pause/stop/accelerate records | D14: Change requires a new crisis or executive intervention | E14: AI maintains decision-ready scenarios and initiates the governed review path
A15: Outcome Calibration & Adaptation | B15: Were the value hypothesis and originating intent preserved before commitment? | C15: Decision record, hypothesis, originating-intent or strategy reference, measures, owner, review date | D15: Success is defined after delivery | E15: The decision can be traced from intent through hypothesis, commitment, and outcome
A16: Outcome Calibration & Adaptation | B16: Can AI connect realized evidence to the original decision without blurring fact and inference? | C16: Evidence package, telemetry, source links, inference labels | D16: Post-hoc narrative substitutes for comparison | E16: Verified evidence, reported information, assumptions, and inference remain distinct
... A19: Outcome Calibration & Adaptation | B19: Can the system distinguish execution failure, forecast error, model error, and possible intent failure? | C19: Failure classification, correction records, authority routing | D19: Every miss is blamed on execution or treated as an isolated incident | E19: Each failure class is routed to the proper correction path, including reconsideration of enterprise intent when warranted

Sheet Reference
A1: Grade | B1: Score | C1: Common Orientation | D1: Cross-model Meaning | F1: Lookup Key | G1: Dimension ID | H1: Dimension | I1: Grade | J1: Level Name | K1: Maturity Definition | L1: Indicative Evidence | M1: Transition to Next Level
A2: A | B2: 1 | C2: Nascent | D2: The capability is mostly implicit, local, or personality-driven. | F2: D1|A | G2: D1 | H2: Value Model Coherence | I2: A | J2: Ad hoc advocacy | K2: Priority is determined mainly by advocacy, urgency, executive request, anecdote, or estimated effort. Individuals may use AI privately to draft business cases or make a preferred item sound more compelling, but there is no stable value model against which the output can be tested. | L2: Roadmaps built from requests; inconsistent rationale; private AI-generated business cases; value and effort discussed as one undifferentiated judgment. | M2: Name a small common set of criteria, separate value from implementation difficulty, and require the same logic for every candidate.
A3: B | B3: 2 | C3: Modeled | D3: A repeatable method exists, with selective AI assistance and uneven governance. | F3: D1|B | G3: D1 | H3: Value Model Coherence | I3: B | J3: Assisted basic scoring | K3: A common prioritization method is used—such as value-versus-effort, RICE, MoSCoW, or a simple weighted score. AI may summarize proposals, normalize submissions, or collect preliminary evidence, but criteria remain generic, scoring anchors are weak, and humans manually translate AI output into the model. | L3: Reusable scorecard; simple ranking; AI-assisted proposal summaries; shared criteria with limited definitions; workshop-dependent interpretation. | M3: Define dimension-specific criteria and scoring anchors, state the evidence expected for material scores, and preserve source provenance.
A4: C | B4: 3 | C4: Continuous | D4: The capability is explicit, shared, traceable, and usable by governed human and AI participants. | F4: D1|C | G4: D1 | H4: Value Model Coherence | I4: C | J4: Structured value model | K4: The organization uses a shared product-value model with distinct scoring dimensions, defined scales, and explicit separation of business value from implementation difficulty. The model is structured enough that AI can map proposals to criteria, assemble cited evidence, identify missing inputs, and flag inconsistent scoring. Humans retain responsibility for weights and final value judgment. | L4: Defined scales and weights; separate business-value and implementation factors; machine-readable scoring structure; cited evidence; AI-flagged gaps or inconsistencies. | M4: Assign formal ownership, version the model, test criteria for overlap or double-counting, and make assumptions, confidence, and exceptions visible.
A5: D | B5: 4 | C5: Integral | D5: The capability is governed, empirically challenged, and connected across portfolio and outcome systems. | F5: D1|D | G5: D1 | H5: Value Model Coherence | I5: D | J5: Governed strategic analysis | K5: The value model is formally owned, versioned, and tied to current strategy and portfolio context. AI performs scenario and sensitivity analysis, challenges unsupported assumptions, detects likely double-counting or scoring drift, and explains why rankings change. The model, weights, evidence standards, and decision authority remain human-governed. | L5: Model owner; version history; criterion provenance; AI-supported sensitivity analysis; confidence notes; scoring-drift review; documented exceptions. | M5: Connect the value model to realized outcomes so evidence can recalibrate scoring anchors, weights, and strategic assumptions.
A6: E | B6: 5 | C6: Telemetric | D6: The capability operates as a durable learning system that can reconsider models, decisions, and intent through proper authority. | F6: D1|E | G6: D1 | H6: Value Model Coherence | I6: E | J6: Adaptive strategic value system | K6: A multi-factor strategic value system—of the kind represented by the Strategic Value Matrix—balances revenue magnitude and velocity, strategic alignment, market and customer fit, architecture, implementation size, technical-debt reduction, and delivery risk through explicit scales and weights. AI continuously refreshes relevant evidence, detects model or strategy drift, and proposes changes to criteria, anchors, or weights. Every change remains explainable, versioned, and human-authorized, and the organization can reconstruct why one item outranked another at any point in time. | L6: Governed strategic value matrix; transparent positive and negative drivers; continuously refreshed evidence; explainable scenarios; model-drift detection; preserved decision history. | M6: Sustain empirical and strategic integrity: verify that evidence refresh improves the model without allowing automation, recency, or persuasive inference to redefine value silently.
F7: D2|A | G7: D2 | H7: Decision Governance & Portfolio Integration | I7: A | J7: Personal authority | K7: Prioritization is a series of local decisions made by the loudest stakeholder, highest-ranking executive, or most urgent customer request. AI may be used privately to strengthen advocacy, but its evidence, reasoning, and influence are invisible. There is no stable decision forum, no visible displacement of other work, and little distinction between recommending, approving, and committing. | L7: Unrecorded overrides; backlog churn; private AI-generated narratives; urgent work inserted without explicit trade-off; no portfolio-level decision record. | M7: Create a recurring decision forum and name who proposes, challenges, decides, records, and commits the outcome.
F8: D2|B | G8: D2 | H8: Decision Governance & Portfolio Integration | I8: B | J8: AI-assisted facilitation | K8: A scorecard or ranking is used in recurring prioritization meetings, and decisions are documented. AI may prepare summaries, compare proposals, expose obvious conflicts, or record rationale, but it has no governed role and lacks complete access to capacity, funding, dependencies, sequencing, and portfolio context. Executives may still override the result without a standard exception path. | L8: Recurring workshop; ranked list; AI-generated meeting preparation; documented decisions; limited constraint analysis; informal overrides. | M8: Define decision rights, an exception path, the portfolio constraints that must be applied, and the specific AI role in evidence assembly and analysis.
F9: D2|C | G9: D2 | H9: Decision Governance & Portfolio Integration | I9: C | J9: Governed portfolio decisions | K9: Scoring, challenge, approval, exception, and commitment are distinct and traceable. AI roles and limits are explicit: AI assembles evidence, checks candidate completeness, verifies dependencies and capacity constraints, and records provenance; named humans make consequential decisions. Funding, sequencing, risk, and portfolio balance constrain the ranked list, and the result directly governs committed work within a portfolio. | L9: Decision log; named authorities; governed AI role; evidence provenance; capacity plan; dependency view; exception record; roadmap traceability. | M9: Extend the same decision system across Product, Engineering, Architecture, Finance, and go-to-market portfolios, with common scenario semantics.
F10: D2|D | G10: D2 | H10: Decision Governance & Portfolio Integration | I10: D | J10: Enterprise portfolio reasoning | K10: A shared prioritization system operates across functions and product areas. AI traverses product, engineering, architecture, finance, customer, and go-to-market evidence to model displacement and second-order effects. Independent analysis can challenge the originating proposal and show what is delayed, unfunded, or made riskier when one investment advances. Humans govern the scenarios, thresholds, and final commitments. | L10: Cross-portfolio scenarios; integrated funding and capacity views; AI-supported displacement analysis; independent challenge; architecture and dependency impacts. | M10: Reduce the latency between material evidence changes and governed reconsideration while preserving authority, evidence, and exception discipline.
F11: D2|E | G11: D2 | H11: Decision Governance & Portfolio Integration | I11: E | J11: Standing adaptive portfolio system | K11: Prioritization operates as a standing management system rather than an episodic workshop. New demand enters through a known path; comparable evidence is assembled; alternatives are challenged; and capacity, funding, dependencies, sequencing, and portfolio balance are resolved continuously. AI monitors material changes, maintains decision-ready scenarios, and initiates governed reconsideration. Routine low-consequence actions may be delegated within explicit authority, while consequential portfolio choices remain visibly human-owned. | L11: Governed intake-to-commit flow; live portfolio scenarios; event-driven reconsideration; bounded AI authority; rapid but traceable continue, pause, stop, accelerate, and reallocate decisions. | M11: Continuously test whether adaptive speed is preserving strategic coherence and constitutional authority rather than amplifying short-term noise.
F12: D3|A | G12: D3 | H12: Outcome Calibration & Adaptation | I12: A | J12: No calibration | K12: Once work is approved, the prioritization decision is rarely revisited. Delivery may be tracked, and AI may summarize results after the fact, but the original value hypothesis, evidence, assumptions, and intended outcome are not preserved well enough to determine whether the decision was right. | L12: Shipped equals successful; no benefits review; no record of original assumptions; post-hoc AI summaries without a comparison baseline. | M12: For every material decision, preserve the expected outcome, measure, owner, review date, underlying value hypothesis, and originating intent.
F13: D3|B | G13: D3 | H13: Outcome Calibration & Adaptation | I13: B | J13: AI-assisted retrospective | K13: Major initiatives receive occasional after-action review. AI helps synthesize retrospectives and compare planned versus actual effort, timing, or selected business outcomes, but the analysis is episodic and selective. Lessons usually affect the next project informally rather than changing the prioritization model or portfolio. | L13: Project retrospectives; AI-assisted synthesis; planned-versus-actual delivery review; informal benefits discussion; isolated lessons. | M13: Require consistent outcome hypotheses and scheduled reviews, and link realized evidence back to the original decision rather than only to delivery performance.
F14: D3|C | G14: D3 | H14: Outcome Calibration & Adaptation | I14: C | J14: Governed outcome linkage | K14: Material prioritization decisions carry explicit expected outcomes, measures, timing, ownership, value hypotheses, and originating intent. AI connects the original decision to subsequent customer, market, financial, delivery, architectural, debt, and risk evidence, flags material variance, and keeps verified evidence, reported information, assumptions, and inference visibly distinct. | L14: Benefits register; decision-to-outcome traceability; named outcome owner; AI-assembled evidence package; forecast-versus-actual review; model-change log. | M14: Measure forecast accuracy and recurring bias by criterion, investment type, product area, and decision team, using independent analysis where practical.
F15: D3|D | G15: D3 | H15: Outcome Calibration & Adaptation | I15: D | J15: Empirical bias correction | K15: AI identifies where the organization systematically overstates value, understates effort, misses timing, discounts risk, or misreads evidence. Forecast accuracy and bias are measured by criterion, team, product area, and investment type. Scoring anchors, confidence ranges, weights, and governance practices are adjusted empirically, and continue, expand, pause, or stop decisions occur before all planned investment is consumed. | L15: Bias analysis; criterion calibration; confidence ranges; independent AI review; stage decisions; evidence-based model revisions; preserved decision lineage. | M15: Close the loop to enterprise intent: distinguish execution failure, forecast error, model error, and possible intent failure, then route each to its proper authority.
F16: D3|E | G16: D3 | H16: Outcome Calibration & Adaptation | I16: E | J16: Closed-loop intent calibration | K16: Product prioritization operates as a continuous learning loop. Customer, market, financial, delivery, architectural, debt, and risk evidence is traced back to the original value hypothesis and the intent it served. AI assistance detects variance, systematic bias, model drift, and emerging opportunity while work is still underway, distinguishing execution failure from forecasting error, model error, and possible intent failure. The portfolio, prioritization model, and—when warranted—the originating intent can each be reconsidered through their proper authority, without losing decision lineage or converting inference into fact. | L16: Continuous outcome signals; intent-to-decision-to-outcome traceability; failure-class diagnosis; model-drift checks; early continue, pause, stop, or redirect decisions; preserved evidence and authority lineage. | M16: Sustain epistemic and constitutional discipline: ensure the loop can challenge intent without allowing AI inference to silently become enterprise intent.

Sheet Intent Loop
A1: The Product Prioritization Intent Loop
A2: D3-E closes the loop from realized outcomes back to the originating enterprise intent.
A4: Enterprise Intent | D4: D1 Value Model Coherence | G4: D2 Decision Governance & Portfolio Integration | J4: Execution & Outcomes
C5: → | F5: → | I5: →
K7: ↓
A9: Reconsider Enterprise Intent when warranted | D9: Correct Portfolio or Value Model | G9: Diagnose Failure Class | J9: D3 Outcome Calibration & Adaptation
C10: ← | F10: ← | I10: ←
A13: D3-E failure classification
A14: Failure class | B14: What failed? | D14: Primary correction | G14: AI-native contribution | K14: Authority
A15: Execution failure | B15: The work did not realize an otherwise sound hypothesis. | D15: Correct delivery, sequencing, capability, or implementation. | G15: Detect variance and assemble evidence without rewriting the original hypothesis. | K15: Delivery / portfolio authority
A16: Forecast error | B16: The value, effort, timing, or risk estimate was wrong. | D16: Calibrate scoring anchors, confidence, and forecasting method. | G16: Identify systematic bias by criterion, team, product area, or investment type. | K16: Model owner / portfolio governance
A17: Model error | B17: The prioritization model omitted, duplicated, or misweighted a material factor. | D17: Revise criteria, weights, evidence standards, or governance. | G17: Detect model drift and propose explainable changes with preserved provenance. | K17: Value-model authority
A18: Possible intent failure | B18: The decision and model may be working against stale, incoherent, or incorrect enterprise intent. | D18: Reconsider originating intent through its proper constitutional authority. | G18: Surface the pattern and evidence; never silently redefine intent. | K18: Enterprise intent authority
A20: AI does not own the loop. It keeps the evidence, alternatives, consequences, and learning continuously available and governable. Human authority remains explicit at every correction point, especially when the evidence reaches back to the organization's originating intent.
